flight_statistics/__init__.py
flight_statistics/statistics.py
flight_statistics-0.1.0.dist-info/METADATA
flight_statistics-0.1.0.dist-info/WHEEL
flight_statistics-0.1.0.dist-info/top_level.txt
flight_statistics-0.1.0.dist-info/RECORD
