Metadata-Version: 2.1
Name: flight_statistics
Version: 0.1.0
Summary: A package to calculate flight statistics
Author: Jocelyn Chen
Author-email: cjl1759648974@outlook.com
